gradescope_autosubmitter/__init__.py
gradescope_autosubmitter/cli.py
gradescope_autosubmitter/config.py
gradescope_autosubmitter/core.py
gradescope_autosubmitter/credentials.py
gradescope_autosubmitter/rich_console.py
gradescope_autosubmitter/ui_config.py
qut_gradescope_autosubmitter-1.0.3.dist-info/METADATA
qut_gradescope_autosubmitter-1.0.3.dist-info/WHEEL
qut_gradescope_autosubmitter-1.0.3.dist-info/entry_points.txt
qut_gradescope_autosubmitter-1.0.3.dist-info/top_level.txt
qut_gradescope_autosubmitter-1.0.3.dist-info/RECORD
