Metadata-Version: 2.4
Name: qut-gradescope-autosubmitter
Version: 1.0.3
Summary: Automated Gradescope submission tool for QUT students with a pretty CLI interface
Author-email: Daniel Sam <daniel.sam@gmx.com>
Project-URL: Homepage, https://github.com/danieltsam/qut-gradescope-autosubmitter
Project-URL: Repository, https://github.com/danieltsam/qut-gradescope-autosubmitter
Project-URL: Issues, https://github.com/danieltsam/qut-gradescope-autosubmitter/issues
Requires-Python: >=3.8
Requires-Dist: playwright>=1.40.0
Requires-Dist: pyyaml>=6.0
Requires-Dist: python-dotenv>=1.0.0
Requires-Dist: click>=8.0.0
Requires-Dist: rich>=13.0.0
